ost_builder/__init__.py
ost_builder/_base_client.py
ost_builder/_client.py
ost_builder/_compat.py
ost_builder/_constants.py
ost_builder/_exceptions.py
ost_builder/_files.py
ost_builder/_models.py
ost_builder/_qs.py
ost_builder/_resource.py
ost_builder/_response.py
ost_builder/_streaming.py
ost_builder/_types.py
ost_builder/_version.py
ost_builder/py.typed
ost_builder/_utils/__init__.py
ost_builder/_utils/_compat.py
ost_builder/_utils/_datetime_parse.py
ost_builder/_utils/_logs.py
ost_builder/_utils/_proxy.py
ost_builder/_utils/_reflection.py
ost_builder/_utils/_resources_proxy.py
ost_builder/_utils/_streams.py
ost_builder/_utils/_sync.py
ost_builder/_utils/_transform.py
ost_builder/_utils/_typing.py
ost_builder/_utils/_utils.py
ost_builder/lib/.keep
ost_builder/resources/__init__.py
ost_builder/resources/exchange.py
ost_builder/resources/health.py
ost_builder/types/__init__.py
ost_builder/types/exchange_cancel_order_params.py
ost_builder/types/exchange_cancel_order_response.py
ost_builder/types/exchange_close_position_params.py
ost_builder/types/exchange_close_position_response.py
ost_builder/types/exchange_modify_order_params.py
ost_builder/types/exchange_modify_order_response.py
ost_builder/types/exchange_open_position_params.py
ost_builder/types/exchange_open_position_response.py
ost_builder/types/exchange_update_margin_params.py
ost_builder/types/exchange_update_margin_response.py
ost_builder/types/health_response.py
ost_builder_test-0.1.1.dist-info/METADATA
ost_builder_test-0.1.1.dist-info/WHEEL
ost_builder_test-0.1.1.dist-info/licenses/LICENSE
ost_builder_test-0.1.1.dist-info/RECORD
